rq_geo_toolkit-2025.9.0.dist-info/METADATA
rq_geo_toolkit-2025.9.0.dist-info/WHEEL
rq_geo_toolkit-2025.9.0.dist-info/entry_points.txt
rq_geo_toolkit-2025.9.0.dist-info/licenses/LICENSE
rq_geo_toolkit/__init__.py
rq_geo_toolkit/_exceptions.py
rq_geo_toolkit/_geopandas_api_version.py
rq_geo_toolkit/constants.py
rq_geo_toolkit/duckdb.py
rq_geo_toolkit/geocode.py
rq_geo_toolkit/geoparquet_compression.py
rq_geo_toolkit/geoparquet_sorting.py
rq_geo_toolkit/multiprocessing_utils.py
rq_geo_toolkit/py.typed
rq_geo_toolkit/rich_utils.py
rq_geo_toolkit-2025.9.0.dist-info/RECORD
