Metadata-Version: 2.1
Name: rq_geo_toolkit
Version: 2025.9.0
Summary: Collection of geo related functions for reuse in other libraries
Author: Kamil Raczycki
License: MIT
Requires-Python: >=3.9
Requires-Dist: geopandas>=1.0
Requires-Dist: shapely>=2.0.6
Requires-Dist: pyarrow>=16.0.0
Requires-Dist: rich>=12.0.0
Requires-Dist: geopy>=2.0.0
Requires-Dist: duckdb>=1.1.2
Requires-Dist: psutil>=5.6.2
Requires-Dist: packaging>=17.0
